rtl/peripheral/gpio_ctrl.v
// ============================================================================
// 模块名   : gpio_ctrl
// 功能描述 : GPIO 控制器 - 4 端口 x16 引脚
//          - 符合 arch_spec_v1.0.md Section 3.1
//          - 每个端口 1KB 地址空间，10 个寄存器
// 作者     : Cortex-M3 SoC RTL Team
// 创建日期 : 2026-03-11
// 版本     : v2.0 (重构版)
// ============================================================================

module gpio_ctrl #(
    parameter   PORT_ID       = 0,          // 端口 ID: 0=A, 1=B, 2=C, 3=D
    parameter   PIN_COUNT     = 16,         // 每端口引脚数
    parameter   APB_ADDR_BASE = 32'h0000    // APB 基地址偏移
) (
    // APB 接口
    input  wire             pclk,
    input  wire             preset_n,
    input  wire             psel,
    input  wire             penable,
    input  wire             pwrite,
    input  wire [31:0]      paddr,
    input  wire [31:0]      pwdata,
    output reg              pready,
    output reg [31:0]       prdata,
    output reg              pslverr,
    
    // GPIO 外部接口
    input  wire [15:0]      gpio_i,         // GPIO 输入
    output reg  [15:0]      gpio_o,         // GPIO 输出
    output reg  [15:0]      gpio_oen,       // GPIO 输出使能
    output wire [15:0]      gpio_irq        // GPIO 中断
);

    //============================================================
    // 寄存器定义 (arch_spec_v1.0.md Section 3.1)
    //============================================================
    
    reg [31:0]  moder_reg;      // 0x00 模式寄存器
    reg [31:0]  otyper_reg;     // 0x04 输出类型
    reg [31:0]  ospeedr_reg;    // 0x08 输出速度
    reg [31:0]  pupdr_reg;      // 0x0C 上下拉
    wire [31:0] idr_wire;       // 0x10 输入数据 (组合逻辑)
    reg [31:0]  odr_reg;        // 0x14 输出数据
    reg [31:0]  bsrr_reg;       // 0x18 置位/复位 (写触发)
    reg [31:0]  lckr_reg;       // 0x1C 锁定寄存器
    reg [31:0]  afrl_reg;       // 0x20 复用功能低
    reg [31:0]  afrh_reg;       // 0x24 复用功能高
    
    // 输入数据直接映射到 IDR
    assign idr_wire = {16'h0000, gpio_i};
    
    //============================================================
    // 中断生成 (输入变化检测)
    //============================================================
    
    reg [15:0]  gpio_i_prev;
    wire [15:0] gpio_i_edge;
    
    assign gpio_irq = gpio_i_edge;
    
    always @(posedge pclk or negedge preset_n) begin
        if (!preset_n)
            gpio_i_prev <= 16'h0000;
        else
            gpio_i_prev <= gpio_i;
    end
    
    assign gpio_i_edge = gpio_i ^ gpio_i_prev;
    
    //============================================================
    // APB 状态机
    //============================================================
    
    reg [1:0] apb_state;
    localparam ST_IDLE = 2'b00, ST_ACCESS = 2'b01;
    
    always @(posedge pclk or negedge preset_n) begin
        if (!preset_n) begin
            apb_state <= ST_IDLE;
            pready <= 1'b0;
            prdata <= 32'h0;
            pslverr <= 1'b0;
        end else begin
            case (apb_state)
                ST_IDLE: begin
                    if (psel && !penable) begin
                        apb_state <= ST_ACCESS;
                        pready <= 1'b0;
                        pslverr <= 1'b0;
                    end
                end
                ST_ACCESS: begin
                    pready <= 1'b1;
                    if (pwrite) begin
                        // 写操作
                        case (paddr[7:2])
                            6'h00: moder_reg   <= pwdata;
                            6'h01: otyper_reg  <= pwdata;
                            6'h02: ospeedr_reg <= pwdata;
                            6'h03: pupdr_reg   <= pwdata;
                            6'h05: begin
                                // ODR 写
                                odr_reg <= pwdata;
                                gpio_o <= pwdata[15:0];
                            end
                            6'h06: begin
                                // BSRR 写 - 原子操作
                                if (pwdata[15:0])  gpio_o <= gpio_o | pwdata[15:0];    // 置位
                                if (pwdata[31:16]) gpio_o <= gpio_o & ~pwdata[31:16];  // 复位
                            end
                            6'h07: lckr_reg  <= pwdata;
                            6'h08: afrl_reg  <= pwdata;
                            6'h09: afrh_reg  <= pwdata;
                            default: pslverr <= 1'b1;
                        endcase
                    end else begin
                        // 读操作
                        case (paddr[7:2])
                            6'h00: prdata <= moder_reg;
                            6'h01: prdata <= otyper_reg;
                            6'h02: prdata <= ospeedr_reg;
                            6'h03: prdata <= pupdr_reg;
                            6'h04: prdata <= idr_wire;
                            6'h05: prdata <= {16'h0000, odr_reg[15:0]};
                            6'h07: prdata <= lckr_reg;
                            6'h08: prdata <= afrl_reg;
                            6'h09: prdata <= afrh_reg;
                            default: prdata <= 32'h0;
                        endcase
                    end
                    apb_state <= ST_IDLE;
                end
            endcase
        end
    end
    
    //============================================================
    // 输出使能生成
    //============================================================
    
    reg [1:0] pin_mode [15:0];
    integer i;
    
    always @(*) begin
        for (i = 0; i < 16; i = i + 1) begin
            pin_mode[i] = moder_reg[i*2 +: 2];
        end
    end
    
    always @(posedge pclk or negedge preset_n) begin
        if (!preset_n) begin
            gpio_oen <= 16'hFFFF;  // 默认输入
        end else if (pwrite && (paddr[7:2] == 6'h00)) begin
            // MODER 更新时重新计算输出使能
            integer j;
            for (j = 0; j < 16; j = j + 1) begin
                case (pwdata[j*2 +: 2])
                    2'b00: gpio_oen[j] <= 1'b1;  // 输入
                    2'b01: gpio_oen[j] <= 1'b0;  // 输出
                    2'b10: gpio_oen[j] <= 1'b0;  // 复用
                    2'b11: gpio_oen[j] <= 1'b1;  // 模拟
                endcase
            end
        end
    end

endmodule

tb/tb_gpio_ctrl.sv
// ============================================================================
// 模块名   : tb_gpio_ctrl
// 功能描述 : GPIO 控制器测试平台
// ============================================================================

`timescale 1ns/1ps

module tb_gpio_ctrl;

    localparam  CLK_PERIOD = 10;  // 100MHz
    
    reg         pclk;
    reg         preset_n;
    reg         psel;
    reg         penable;
    reg         pwrite;
    reg  [31:0] paddr;
    reg  [31:0] pwdata;
    wire        pready;
    wire [31:0] prdata;
    wire        pslverr;
    
    reg  [15:0] gpio_i;
    wire [15:0] gpio_o;
    wire [15:0] gpio_oen;
    wire [15:0] gpio_irq;
    
    integer     tests_passed;
    integer     tests_failed;
    
    gpio_ctrl #(
        .PORT_ID   (0),
        .PIN_COUNT (16)
    ) u_gpio (
        .pclk      (pclk),
        .preset_n  (preset_n),
        .psel      (psel),
        .penable   (penable),
        .pwrite    (pwrite),
        .paddr     (paddr),
        .pwdata    (pwdata),
        .pready    (pready),
        .prdata    (prdata),
        .pslverr   (pslverr),
        .gpio_i    (gpio_i),
        .gpio_o    (gpio_o),
        .gpio_oen  (gpio_oen),
        .gpio_irq  (gpio_irq)
    );
    
    always # (CLK_PERIOD/2) pclk = ~pclk;
    
    initial begin
        pclk = 0;
        preset_n = 0;
        psel = 0;
        penable = 0;
        pwrite = 0;
        paddr = 32'h0;
        pwdata = 32'h0;
        gpio_i = 16'h0;
        
        tests_passed = 0;
        tests_failed = 0;
        
        #20 preset_n = 1;
        #20;
        
        $display("");
        $display("========================================");
        $display("  GPIO Controller Test");
        $display("========================================");
        $display("");
        
        test_moder();
        test_odr_bsrr();
        test_input_read();
        test_irq();
        
        $display("");
        $display("========================================");
        $display("  Test Summary");
        $display("========================================");
        $display("  Passed: %0d", tests_passed);
        $display("  Failed: %0d", tests_failed);
        $display("========================================");
        
        if (tests_failed == 0) begin
            $display("✓ All tests PASSED!");
            $finish;
        end else begin
            $display("✗ Some tests FAILED!");
            $finish(1);
        end
    end
    
    task apb_write;
        input [31:0] addr;
        input [31:0] data;
        begin
            @(posedge pclk);
            paddr = addr;
            pwdata = data;
            pwrite = 1;
            psel = 1;
            penable = 0;
            @(posedge pclk);
            penable = 1;
            wait (pready);
            @(posedge pclk);
            psel = 0;
            penable = 0;
            pwrite = 0;
        end
    endtask
    
    task apb_read_check;
        input [31:0] addr;
        input [31:0] expected;
        reg [31:0] actual;
        begin
            @(posedge pclk);
            paddr = addr;
            pwrite = 0;
            psel = 1;
            penable = 0;
            @(posedge pclk);
            penable = 1;
            wait (pready);
            actual = prdata;
            @(posedge pclk);
            psel = 0;
            penable = 0;
            
            if (actual !== expected) begin
                $display("    Read mismatch: addr=0x%08h, expected=0x%08h, actual=0x%08h", addr, expected, actual);
                tests_failed = tests_failed + 1;
            end else begin
                tests_passed = tests_passed + 1;
            end
        end
    endtask
    
    task test_moder;
        begin
            $display("[TEST] MODER Register");
            
            apb_write(32'h00, 32'h55555555);
            apb_read_check(32'h00, 32'h55555555);
            $display("  MODER test completed");
            
            apb_write(32'h00, 32'h0);
        end
    endtask
    
    task test_odr_bsrr;
        begin
            $display("[TEST] ODR and BSRR");
            
            apb_write(32'h14, 32'hAAAA);
            if (gpio_o !== 16'hAAAA) begin
                $display("  ✗ ODR write failed, got 0x%04h", gpio_o);
                tests_failed = tests_failed + 1;
            end else begin
                $display("  ✓ ODR write passed");
                tests_passed = tests_passed + 1;
            end
            
            apb_write(32'h18, 32'h00010000);
            if (gpio_o[0] !== 1'b0) begin
                $display("  ✗ BSRR reset failed");
                tests_failed = tests_failed + 1;
            end else begin
                $display("  ✓ BSRR reset passed");
                tests_passed = tests_passed + 1;
            end
            
            apb_write(32'h18, 32'h00000001);
            if (gpio_o[0] !== 1'b1) begin
                $display("  ✗ BSRR set failed");
                tests_failed = tests_failed + 1;
            end else begin
                $display("  ✓ BSRR set passed");
                tests_passed = tests_passed + 1;
            end
        end
    endtask
    
    task test_input_read;
        begin
            $display("[TEST] Input Read (IDR)");
            
            gpio_i = 16'hBEEF;
            #1;
            apb_read_check(32'h10, {16'h0000, 16'hBEEF});
            $display("  IDR test completed");
        end
    endtask
    
    task test_irq;
        begin
            $display("[TEST] IRQ Generation");
            
            // 稳定状态
            gpio_i = 16'h0000;
            @(posedge pclk);
            @(posedge pclk);
            
            // 输入变化 - 在 clock edge 之前变化，检测 edge 信号
            #1;
            gpio_i = 16'hFFFF;
            #1;  // 等待组合逻辑传播
            
            if (gpio_irq !== 16'hFFFF) begin
                $display("  ✗ IRQ generation failed (expected 0xFFFF, got 0x%04h)", gpio_irq);
                tests_failed = tests_failed + 1;
            end else begin
                $display("  ✓ IRQ generation passed");
                tests_passed = tests_passed + 1;
            end
            
            // 等待下一个 clock，确认 edge 被捕获并更新 prev
            @(posedge pclk);
        end
    endtask
    
    initial begin
        $dumpfile("tb_gpio_ctrl.vcd");
        $dumpvars(0, tb_gpio_ctrl);
    end

endmodule

sim/tb_gpio_ctrl.vcd
$date
	Wed Mar 11 10:25:28 2026
$end
$version
	Icarus Verilog
$end
$timescale
	1ps
$end
$scope module tb_gpio_ctrl $end
$var wire 1 ! pslverr $end
$var wire 1 " pready $end
$var wire 32 # prdata [31:0] $end
$var wire 16 $ gpio_oen [15:0] $end
$var wire 16 % gpio_o [15:0] $end
$var wire 16 & gpio_irq [15:0] $end
$var parameter 32 ' CLK_PERIOD $end
$var reg 16 ( gpio_i [15:0] $end
$var reg 32 ) paddr [31:0] $end
$var reg 1 * pclk $end
$var reg 1 + penable $end
$var reg 1 , preset_n $end
$var reg 1 - psel $end
$var reg 32 . pwdata [31:0] $end
$var reg 1 / pwrite $end
$var integer 32 0 tests_failed [31:0] $end
$var integer 32 1 tests_passed [31:0] $end
$scope module u_gpio $end
$var wire 16 2 gpio_i [15:0] $end
$var wire 16 3 gpio_i_edge [15:0] $end
$var wire 16 4 gpio_irq [15:0] $end
$var wire 32 5 paddr [31:0] $end
$var wire 1 * pclk $end
$var wire 1 + penable $end
$var wire 1 , preset_n $end
$var wire 1 - psel $end
$var wire 32 6 pwdata [31:0] $end
$var wire 1 / pwrite $end
$var wire 32 7 idr_wire [31:0] $end
$var parameter 32 8 APB_ADDR_BASE $end
$var parameter 32 9 PIN_COUNT $end
$var parameter 32 : PORT_ID $end
$var parameter 2 ; ST_ACCESS $end
$var parameter 2 < ST_IDLE $end
$var reg 32 = afrh_reg [31:0] $end
$var reg 32 > afrl_reg [31:0] $end
$var reg 2 ? apb_state [1:0] $end
$var reg 16 @ gpio_i_prev [15:0] $end
$var reg 16 A gpio_o [15:0] $end
$var reg 16 B gpio_oen [15:0] $end
$var reg 32 C lckr_reg [31:0] $end
$var reg 32 D moder_reg [31:0] $end
$var reg 32 E odr_reg [31:0] $end
$var reg 32 F ospeedr_reg [31:0] $end
$var reg 32 G otyper_reg [31:0] $end
$var reg 32 H prdata [31:0] $end
$var reg 1 " pready $end
$var reg 1 ! pslverr $end
$var reg 32 I pupdr_reg [31:0] $end
$var integer 32 J i [31:0] $end
$scope begin $unm_blk_16 $end
$var integer 32 K j [31:0] $end
$upscope $end
$upscope $end
$scope task apb_read_check $end
$var reg 32 L actual [31:0] $end
$var reg 32 M addr [31:0] $end
$var reg 32 N expected [31:0] $end
$upscope $end
$scope task apb_write $end
$var reg 32 O addr [31:0] $end
$var reg 32 P data [31:0] $end
$upscope $end
$scope task test_input_read $end
$upscope $end
$scope task test_irq $end
$upscope $end
$scope task test_moder $end
$upscope $end
$scope task test_odr_bsrr $end
$upscope $end
$upscope $end
$enddefinitions $end
$comment Show the parameter values. $end
$dumpall
b0 <
b1 ;
b0 :
b10000 9
b0 8
b1010 '
$end
#0
$dumpvars
bx P
bx O
bx N
bx M
bx L
bx K
bx J
bx I
b0 H
bx G
bx F
bx E
bx D
bx C
b1111111111111111 B
bx A
b0 @
b0 ?
bx >
bx =
b0 7
b0 6
b0 5
b0 4
b0 3
b0 2
b0 1
b0 0
0/
b0 .
0-
0,
0+
0*
b0 )
b0 (
b0 &
bx %
b1111111111111111 $
b0 #
0"
0!
$end
#5000
1*
#10000
0*
#15000
1*
#20000
0*
1,
#25000
1*
#30000
0*
#35000
1*
#40000
0*
b1010101010101010101010101010101 P
b0 O
#45000
b0 $
b0 B
b1 ?
b10000 K
1-
1/
b1010101010101010101010101010101 .
b1010101010101010101010101010101 6
1*
#50000
0*
#55000
b10000 J
b0 ?
b1010101010101010101010101010101 D
1"
b10000 K
1+
1*
#60000
0*
#65000
b1010101010101010101010101010101 N
b0 M
0/
0+
0-
1*
#70000
0*
#75000
0"
b1 ?
1-
1*
#80000
0*
#85000
b1010101010101010101010101010101 L
b0 ?
b1010101010101010101010101010101 #
b1010101010101010101010101010101 H
1"
1+
1*
#90000
0*
#95000
b0 P
b1 1
0+
0-
1*
#100000
0*
#105000
b1111111111111111 $
b1111111111111111 B
0"
b1 ?
b10000 K
1-
1/
b0 .
b0 6
1*
#110000
0*
#115000
b10000 J
b0 ?
b0 D
1"
b10000 K
1+
1*
#120000
0*
#125000
b1010101010101010 P
b10100 O
0/
0+
0-
1*
#130000
0*
#135000
0"
b1 ?
1-
1/
b1010101010101010 .
b1010101010101010 6
b10100 )
b10100 5
1*
#140000
0*
#145000
b0 ?
b1010101010101010 %
b1010101010101010 A
b1010101010101010 E
1"
1+
1*
#150000
0*
#155000
b10000000000000000 P
b11000 O
b10 1
0/
0+
0-
1*
#160000
0*
#165000
0"
b1 ?
1-
1/
b10000000000000000 .
b10000000000000000 6
b11000 )
b11000 5
1*
#170000
0*
#175000
b0 ?
1"
1+
1*
#180000
0*
#185000
b1 P
b11 1
0/
0+
0-
1*
#190000
0*
#195000
0"
b1 ?
1-
1/
b1 .
b1 6
1*
#200000
0*
#205000
b0 ?
b1010101010101011 %
b1010101010101011 A
1"
1+
1*
#210000
0*
#215000
b1011111011101111 @
b0 &
b0 4
b0 3
b1011111011101111 7
b1011111011101111 (
b1011111011101111 2
b100 1
0/
0+
0-
1*
#216000
b1011111011101111 N
b10000 M
#220000
0*
#225000
0"
b1 ?
1-
b10000 )
b10000 5
1*
#230000
0*
#235000
b1011111011101111 L
b0 ?
b1011111011101111 #
b1011111011101111 H
1"
1+
1*
#240000
0*
#245000
b0 @
b0 &
b0 4
b0 3
b0 7
b0 (
b0 2
b101 1
0+
0-
1*
#250000
0*
#255000
b1111111111111111 @
b0 &
b0 4
b0 3
b1111111111111111 7
b1111111111111111 (
b1111111111111111 2
1*
#260000
0*
#265000
b1 0
1*
